setup.cfg
setup.py
A1nzz_serializer.egg-info/PKG-INFO
A1nzz_serializer.egg-info/SOURCES.txt
A1nzz_serializer.egg-info/dependency_links.txt
A1nzz_serializer.egg-info/requires.txt
A1nzz_serializer.egg-info/top_level.txt
Serializers/__init__.py
Serializers/base_serializer.py
Serializers/constants.py
Serializers/dict_serializer.py
Serializers/json_serializer.py
Serializers/serializers_factory.py
Serializers/xml_serializer.py