Metadata-Version: 2.1
Name: A1nzz-serializer
Version: 1.0
Summary: module for python (de)serialization in Json and Xml
Home-page: https://github.com/A1nzz/Python-Labs/tree/Lab3
Author: Mamchenko Kirill
Author-email: kmamcenko@gmail.com
License: MIT
Platform: UNKNOWN
Classifier: Intended Audience :: Developers
Classifier: Programming Language :: Python :: 3.10
Classifier: Operating System :: OS Independent
